{"ok":true,"action":"all","algorithms":[{"source":"stock_picks","algorithm":"ETF Masters","win_rate":82.35,"avg_win":2.3067,"avg_loss":1.2706,"trades":17,"full_kelly":0.25,"recommended_pct":6.3,"edge":1.3185,"has_edge":true},{"source":"stock_picks","algorithm":"Blue Chip Growth","win_rate":80,"avg_win":5.6037,"avg_loss":3.7951,"trades":25,"full_kelly":0.25,"recommended_pct":6.3,"edge":0.9812,"has_edge":true},{"source":"stock_picks","algorithm":"Cursor Genius","win_rate":85.71,"avg_win":8.1132,"avg_loss":6.2167,"trades":14,"full_kelly":0.25,"recommended_pct":6.3,"edge":0.9757,"has_edge":true},{"source":"stock_picks","algorithm":"Sector Rotation","win_rate":72.73,"avg_win":3.1901,"avg_loss":2.3814,"trades":11,"full_kelly":0.25,"recommended_pct":6.3,"edge":0.7016,"has_edge":true},{"source":"stock_picks","algorithm":"Composite Rating","win_rate":50,"avg_win":5.981,"avg_loss":6.5212,"trades":12,"full_kelly":0,"recommended_pct":0,"edge":-0.0414,"has_edge":false},{"source":"stock_picks","algorithm":"Technical Momentum","win_rate":25,"avg_win":6.2113,"avg_loss":4.8001,"trades":12,"full_kelly":0,"recommended_pct":0,"edge":-0.4265,"has_edge":false},{"source":"stock_picks","algorithm":"Sector Momentum","win_rate":0,"avg_win":0,"avg_loss":98.6291,"trades":84,"full_kelly":0,"recommended_pct":0,"edge":null,"has_edge":false}],"count":7,"with_edge":4,"without_edge":3}